starknet_devnet/ERC20_Mintable_OZ_0.2.0.json
starknet_devnet/MockStarknetMessaging.json
starknet_devnet/UDC_OZ_0.5.0.json
starknet_devnet/__init__.py
starknet_devnet/account.py
starknet_devnet/account_util.py
starknet_devnet/accounts.py
starknet_devnet/accounts_artifacts/OpenZeppelin/0.5.1/Account.cairo/Account.json
starknet_devnet/accounts_artifacts/OpenZeppelin/0.5.1/Account.cairo/Account_abi.json
starknet_devnet/block_info_generator.py
starknet_devnet/blocks.py
starknet_devnet/blueprints/__init__.py
starknet_devnet/blueprints/base.py
starknet_devnet/blueprints/feeder_gateway.py
starknet_devnet/blueprints/gateway.py
starknet_devnet/blueprints/postman.py
starknet_devnet/blueprints/rpc/__init__.py
starknet_devnet/blueprints/rpc/blocks.py
starknet_devnet/blueprints/rpc/call.py
starknet_devnet/blueprints/rpc/classes.py
starknet_devnet/blueprints/rpc/misc.py
starknet_devnet/blueprints/rpc/routes.py
starknet_devnet/blueprints/rpc/rpc_spec.py
starknet_devnet/blueprints/rpc/rpc_spec_write.py
starknet_devnet/blueprints/rpc/rpc_trace_spec.py
starknet_devnet/blueprints/rpc/schema.py
starknet_devnet/blueprints/rpc/state.py
starknet_devnet/blueprints/rpc/storage.py
starknet_devnet/blueprints/rpc/structures/__init__.py
starknet_devnet/blueprints/rpc/structures/payloads.py
starknet_devnet/blueprints/rpc/structures/responses.py
starknet_devnet/blueprints/rpc/structures/types.py
starknet_devnet/blueprints/rpc/transactions.py
starknet_devnet/blueprints/rpc/utils.py
starknet_devnet/blueprints/shared.py
starknet_devnet/cairo_rs_py_patch.py
starknet_devnet/chargeable_account.py
starknet_devnet/compiler.py
starknet_devnet/constants.py
starknet_devnet/contract_class_wrapper.py
starknet_devnet/devnet_config.py
starknet_devnet/dump.py
starknet_devnet/fee_token.py
starknet_devnet/forked_state.py
starknet_devnet/general_config.py
starknet_devnet/origin.py
starknet_devnet/postman_wrapper.py
starknet_devnet/predeployed_contract_wrapper.py
starknet_devnet/server.py
starknet_devnet-0.6.5.dist-info/entry_points.txt
starknet_devnet-0.6.5.dist-info/WHEEL
starknet_devnet-0.6.5.dist-info/METADATA
starknet_devnet-0.6.5.dist-info/LICENSE
starknet_devnet-0.6.5.dist-info/RECORD
